{"chunk_definitions":[{"chunk_id":"c2dzbw02x982d","expansion_state":0,"options":[],"row":9,"row_count":1,"visible":true},{"chunk_id":"cwlya0jt1fwhf","expansion_state":0,"options":[],"row":16,"row_count":1,"visible":true},{"chunk_id":"ce43dss0twpdq","expansion_state":0,"options":[],"row":25,"row_count":1,"visible":true},{"chunk_id":"ci9u1bo5q13b2","expansion_state":0,"options":[],"row":34,"row_count":1,"visible":true},{"chunk_id":"c0c5ifi67o4tb","expansion_state":0,"options":[],"row":44,"row_count":1,"visible":true},{"chunk_id":"c901odb7gxjv6","expansion_state":0,"options":[],"row":52,"row_count":1,"visible":true}],"doc_write_time":1604376363.37386}
